panoply/__init__.py
panoply/__main__.py
panoply/__version__.py
panoply/commands.txt
panoply/panoply.py
panoply-0.1.56.dist-info/entry_points.txt
panoply-0.1.56.dist-info/WHEEL
panoply-0.1.56.dist-info/METADATA
panoply-0.1.56.dist-info/RECORD
